{
  "type": "minecraft:smithing_transform",
  "template": "minecraft:snow_golem_spawn_egg",
  "base": "minecraft:diamond_sword",
  "addition": "minecraft:copper_ingot",
  "result": {
    "id": "minecraft:diamond_sword",
    "count": 1,
    "components": {
      "minecraft:trim": {
        "pattern": "tooltrims:frost",
        "material": "minecraft:copper"
      },
      "minecraft:custom_model_data": {
        "floats": [ 311032.0 ]
      },
      "minecraft:custom_data": {
        "tooltrims:item": "fresh_trim"
      }
    }
  },
  "show_notification": false
}